ios_notification-0.1.3.dist-info/DESCRIPTION.rst
ios_notification-0.1.3.dist-info/METADATA
ios_notification-0.1.3.dist-info/RECORD
ios_notification-0.1.3.dist-info/WHEEL
ios_notification-0.1.3.dist-info/metadata.json
ios_notification-0.1.3.dist-info/top_level.txt
ios_notification-0.1.3.dist-info/zip-safe
ios_notifications/__init__.py
ios_notifications/settings.py
ios_notifications/urls.py
ios_notifications/wsgi.py
notification/__init__.py
notification/admin.py
notification/apps.py
notification/forms.py
notification/models.py
notification/urls.py
notification/utils.py
notification/views.py
notification/apns/__init__.py
notification/apns/apns.py
notification/files/__init__.py
notification/management/__init__.py
notification/management/commands/__init__.py
notification/management/commands/multipush.py
notification/management/commands/singlepush.py
notification/migrations/0001_initial.py
notification/migrations/0002_certfile.py
notification/migrations/0003_auto_20170528_0003.py
notification/migrations/0004_devicetoken_use_sandbox.py
notification/migrations/0005_auto_20180218_0454.py
notification/migrations/__init__.py
notification/templates/base.html
notification/templates/login.html
notification/templates/logout.html
notification/templates/upload.html
notification/tests/__init__.py
notification/tests/compatibility.py
notification/tests/test_device_token.py
notification/tests/test_notification_command_multipush.py
notification/tests/test_notification_command_singlepush.py
notification/tests/test_notification_forms.py
notification/tests/test_notification_utils.py
notification/tests/test_notification_views.py
tests/__init__.py
tests/settings.py
tests/urls.py
