Metadata-Version: 2.0
Name: ios-notification
Version: 0.1.3
Summary: A Django plugin for Apple Notification Service
Home-page: https://github.com/nnsnodnb/django-ios-notifications
Author: nnsnodnb
Author-email: ahr63_gej@me.com
License: MIT
Download-URL: https://github.com/nnsnodnb/django-ios-notifications/tarball/master
Keywords: django ios push notification apple apns
Platform: UNKNOWN
Classifier: Development Status :: 5 - Production/Stable
Classifier: Environment :: Web Environment
Classifier: Framework :: Django
Classifier: Intended Audience :: Developers
Classifier: License :: OSI Approved :: MIT License
Classifier: Programming Language :: Python
Classifier: Programming Language :: Python :: 2
Classifier: Programming Language :: Python :: 2.7
Classifier: Programming Language :: Python :: 3
Classifier: Programming Language :: Python :: 3.4
Classifier: Programming Language :: Python :: 3.5
Classifier: Programming Language :: Python :: 3.6
Classifier: Topic :: Internet :: WWW/HTTP
Classifier: Topic :: Software Development :: Libraries
Classifier: Topic :: Software Development :: Libraries :: Application Frameworks
Classifier: Topic :: Software Development :: Libraries :: Python Modules
Requires-Dist: appdirs (==1.4.3)
Requires-Dist: dateutils (==0.6.6)
Requires-Dist: Django (>=1.7)
Requires-Dist: mock (==2.0.0)
Requires-Dist: packaging (==16.8)
Requires-Dist: pbr (==3.1.1)
Requires-Dist: pyparsing (==2.2.0)
Requires-Dist: python-dateutil (==2.6.1)
Requires-Dist: pytz (==2017.3)
Requires-Dist: six (==1.11.0)
